pps_gui/Day.png
pps_gui/Night.png
pps_gui/Ouch.png
pps_gui/__init__.py
pps_gui/buzzer.wav
pps_gui-2.25.dist-info/LICENSE
pps_gui-2.25.dist-info/METADATA
pps_gui-2.25.dist-info/WHEEL
pps_gui-2.25.dist-info/entry_points.txt
pps_gui-2.25.dist-info/top_level.txt
pps_gui-2.25.dist-info/RECORD
